yapymake/__init__.py
yapymake/args.py
yapymake/makefile/__init__.py
yapymake/makefile/parse_util.py
yapymake/makefile/token.py
yapymake/util/__init__.py
yapymake/util/peekable_iterator.py
yapymake-0.2.0.dist-info/LICENSE.md
yapymake-0.2.0.dist-info/METADATA
yapymake-0.2.0.dist-info/WHEEL
yapymake-0.2.0.dist-info/entry_points.txt
yapymake-0.2.0.dist-info/top_level.txt
yapymake-0.2.0.dist-info/RECORD
