Metadata-Version: 2.1
Name: yapymake
Version: 0.2.0
Summary: A (mostly) POSIX-compatible make implemented in Python
Home-page: https://code.boringcactus.com/yapymake/
Author: Melody Horn / boringcactus
Author-email: melody@boringcactus.com
License: UNKNOWN
Keywords: build,make
Platform: UNKNOWN
Classifier: Environment :: Console
Classifier: Intended Audience :: Developers
Classifier: License :: Other/Proprietary License
Classifier: Operating System :: OS Independent
Classifier: Topic :: Software Development :: Build Tools
